README.md
setup.py
webscapy/__init__.py
webscapy/webscapy.py
webscapy.egg-info/PKG-INFO
webscapy.egg-info/SOURCES.txt
webscapy.egg-info/dependency_links.txt
webscapy.egg-info/not-zip-safe
webscapy.egg-info/requires.txt
webscapy.egg-info/top_level.txt