Metadata-Version: 2.1
Name: webscapy
Version: 1.6.5
Summary: Selenium built for scraping instead of testing
Author: Rahul Raj
Project-URL: Documentation, https://pypi.org/project/webscapy/
Project-URL: Source, https://pypi.org/project/webscapy/
